{
    "totalSales": {
        "option": {
            "dateFrom": "2023-01-01",
            "dateTo": "2023-01-31",
            "brands": [
                "trx",
                "mpro"
            ]
        },
        "staff": [
            {
                "tanaka": {
                    "trx": 50000,
                    "mpro": 50000,
                    "id":3,
                },
                "yoshida": {
                    "trx": 50000,
                    "mpro": 50000,
                    "id":9,
                }
            }
        ]
    },
    "totalOrders": {
        "option": {
            "dateFrom": "2023-01-01",
            "dateTo": "2023-01-31",
            "brands": [
                "trx",
                "mpro"
            ]
        },
        "staff": [
            {
                "tanaka": {
                    "total": 7,
                    "new": 3
                },
                "yoshida": {
                    "total": 10,
                    "new": 5
                }
            }
        ]
    }
}
